lightningrobot_plugin_test/__init__.py
lightningrobot_plugin_test-0.1.1.dist-info/METADATA
lightningrobot_plugin_test-0.1.1.dist-info/WHEEL
lightningrobot_plugin_test-0.1.1.dist-info/RECORD
